mlflow_baidubce_store_plugin/__init__.py
mlflow_baidubce_store_plugin/bce_bos_artifact_repo.py
mlflow_baidubce_store_plugin-1.0.7.dist-info/LICENSE
mlflow_baidubce_store_plugin-1.0.7.dist-info/METADATA
mlflow_baidubce_store_plugin-1.0.7.dist-info/WHEEL
mlflow_baidubce_store_plugin-1.0.7.dist-info/entry_points.txt
mlflow_baidubce_store_plugin-1.0.7.dist-info/top_level.txt
mlflow_baidubce_store_plugin-1.0.7.dist-info/RECORD
