Metadata-Version: 2.1
Name: mlflow-baidubce-store-plugin
Version: 1.0.7
Summary: A MLflow plugin that allows users to use Baidu BCE BOS as the artifact store for MLflow.
Home-page: https://github.com/arcosx/mlflow-baidubcestore
Author: arcosx
Author-email: arcosx@outlook.com
License: Apache License 2.0
License-File: LICENSE
Requires-Dist: mlflow
Requires-Dist: bce-python-sdk
